LICENSE
MANIFEST.in
README.rst
setup.cfg
setup.py
DPark.egg-info/PKG-INFO
DPark.egg-info/SOURCES.txt
DPark.egg-info/dependency_links.txt
DPark.egg-info/not-zip-safe
DPark.egg-info/requires.txt
DPark.egg-info/top_level.txt
dpark/__init__.py
dpark/accumulator.py
dpark/bagel.py
dpark/broadcast.py
dpark/cache.py
dpark/conf.py
dpark/context.py
dpark/dependency.py
dpark/dstream.py
dpark/env.py
dpark/executor.py
dpark/hostatus.py
dpark/job.py
dpark/mutable_dict.py
dpark/portable_hash.pyx
dpark/rdd.py
dpark/schedule.py
dpark/serialize.py
dpark/shuffle.py
dpark/table.py
dpark/tabular.py
dpark/task.py
dpark/tracker.py
dpark/file_manager/__init__.py
dpark/file_manager/consts.py
dpark/file_manager/fs.py
dpark/file_manager/mfs_proxy.py
dpark/file_manager/utils.py
dpark/utils/__init__.py
dpark/utils/beansdb.py
dpark/utils/bitindex.py
dpark/utils/crc32c.c
dpark/utils/crc32c_mod.c
dpark/utils/debug.py
dpark/utils/frame.py
dpark/utils/heaponkey.py
dpark/utils/hotcounter.py
dpark/utils/hyperloglog.py
dpark/utils/log.py
dpark/utils/lz4wrapper.py
dpark/utils/memory.py
dpark/utils/nested_groupby.py
dpark/utils/profile.py
dpark/utils/tdigest.py
dpark/web/__init__.py
dpark/web/ui/__init__.py
dpark/web/ui/static/css/bootstrap.min.css
dpark/web/ui/static/css/dag-viz.css
dpark/web/ui/static/js/bootstrap-tooltip.js
dpark/web/ui/static/js/d3.min.js
dpark/web/ui/static/js/dag-viz.js
dpark/web/ui/static/js/dagre-d3.min.js
dpark/web/ui/static/js/graphlib-dot.min.js
dpark/web/ui/static/js/jquery-1.11.1.min.js
dpark/web/ui/templates/index.html
dpark/web/ui/templates/jobs.html
dpark/web/ui/templates/layout.html
dpark/web/ui/templates/stages.html
dpark/web/ui/views/__init__.py
dpark/web/ui/views/index.py
dpark/web/ui/views/rddopgraph.py
examples/dgrep
tools/dquery
tools/drun
tools/executor.py
tools/mrun
tools/scheduler.py