Metadata-Version: 1.1
Name: DPark
Version: 0.5.0
Summary: Python clone of Spark, MapReduce like computing framework supporting iterative algorithms.
Home-page: https://github.com/douban/dpark
Author: Davies Liu
Author-email: davies.liu@gmail.com
License: BSD License
Download-URL: https://github.com/douban/dpark/archive/0.5.0.tar.gz
Keywords: dpark python mapreduce spark
Platform: UNKNOWN
Classifier: Programming Language :: Python
Classifier: Intended Audience :: Developers
Classifier: License :: OSI Approved :: BSD License
Classifier: Operating System :: POSIX
